memory_hub/__init__.py
memory_hub/cli.py
memory_hub/http_cli.py
memory_hub/http_server.py
memory_hub/mcp_server.py
memory_hub/core/__init__.py
memory_hub/core/auth.py
memory_hub/core/chunking.py
memory_hub/core/config.py
memory_hub/core/models.py
memory_hub/core/services.py
memory_hub/core/handlers/__init__.py
memory_hub/core/handlers/health_handlers.py
memory_hub/core/handlers/list_handlers.py
memory_hub/core/handlers/memory/__init__.py
memory_hub/core/handlers/memory/add.py
memory_hub/core/handlers/memory/delete.py
memory_hub/core/handlers/memory/export.py
memory_hub/core/handlers/memory/hierarchy.py
memory_hub/core/handlers/memory/project.py
memory_hub/core/handlers/memory/quickstart.py
memory_hub/core/handlers/memory/recent.py
memory_hub/core/handlers/memory/search.py
memory_hub/core/handlers/memory/session.py
memory_hub/core/handlers/memory/update.py
memory_hub/core/handlers/memory/utils.py
memory_hub/core/utils/__init__.py
memory_hub/core/utils/dependencies.py
memory_hub/core/utils/search_utils.py
memory_hub/core/utils/validation.py
memory_hub_mcp-1.11.0.dist-info/METADATA
memory_hub_mcp-1.11.0.dist-info/WHEEL
memory_hub_mcp-1.11.0.dist-info/entry_points.txt
memory_hub_mcp-1.11.0.dist-info/RECORD
