Metadata-Version: 2.4
Name: memory-hub-mcp
Version: 1.11.0
Summary: Local Memory Hub MCP Server with stdio transport for ZenCoder and MCP clients
Author: Matt
License: MIT
Keywords: ai,mcp,memory,stdio,vector-search,zencoder
Classifier: Development Status :: 3 - Alpha
Classifier: Intended Audience :: Developers
Classifier: License :: OSI Approved :: MIT License
Classifier: Programming Language :: Python :: 3
Classifier: Programming Language :: Python :: 3.11
Classifier: Programming Language :: Python :: 3.12
Requires-Python: >=3.11
Requires-Dist: fastapi>=0.115.0
Requires-Dist: httpx>=0.28.1
Requires-Dist: mcp==1.9.3
Requires-Dist: pydantic>=2.11.5
Requires-Dist: python-dotenv>=1.1.0
Requires-Dist: pyyaml>=6.0.1
Requires-Dist: qdrant-client>=1.14.2
Requires-Dist: semchunk>=3.2.1
Requires-Dist: uvicorn[standard]>=0.32.0
Provides-Extra: dev
Requires-Dist: black; extra == 'dev'
Requires-Dist: pytest; extra == 'dev'
Requires-Dist: pytest-asyncio; extra == 'dev'
Requires-Dist: ruff; extra == 'dev'
